imcii/__init__.py
imcii/ascii.py
imcii-0.1.5.dist-info/DESCRIPTION.rst
imcii-0.1.5.dist-info/METADATA
imcii-0.1.5.dist-info/RECORD
imcii-0.1.5.dist-info/WHEEL
imcii-0.1.5.dist-info/entry_points.txt
imcii-0.1.5.dist-info/metadata.json
imcii-0.1.5.dist-info/top_level.txt
