Metadata-Version: 2.0
Name: imcii
Version: 0.1.5
Summary: imcii = Image to ASCII
Home-page: https://windard.com
Author: Windard Yang
Author-email: windard@qq.com
License: MIT
Platform: UNKNOWN
